d_back/__init__.py
d_back/__main__.py
d_back/server.py
d_back/dist/index.html
d_back/mock/__init__.py
d_back/mock/data.py
d_back-0.0.18.dist-info/LICENSE
d_back-0.0.18.dist-info/METADATA
d_back-0.0.18.dist-info/WHEEL
d_back-0.0.18.dist-info/entry_points.txt
d_back-0.0.18.dist-info/top_level.txt
d_back-0.0.18.dist-info/RECORD
