Metadata-Version: 2.1
Name: d_back
Version: 0.0.18
Summary: WebSocket server project.
Author: Tin Nguyen
Author-email: Tin Nguyen <nguyen.ngoctindaniel@gmail.com>
Requires-Python: >=3.8
License-File: LICENSE
Requires-Dist: websockets<14.0,>=10.0; python_version < "3.10"
Requires-Dist: websockets<16.0,>=10.0; python_version >= "3.10"
Provides-Extra: docs
Requires-Dist: mkdocs>=1.5.0; extra == "docs"
Requires-Dist: mkdocs-material>=9.5.0; extra == "docs"
Requires-Dist: mkdocs-static-i18n>=1.2.0; extra == "docs"
Requires-Dist: mkdocstrings[python]>=0.24.0; extra == "docs"
Requires-Dist: mkdocstrings-python>=1.8.0; extra == "docs"
Requires-Dist: pymdown-extensions>=10.7; extra == "docs"
Requires-Dist: mike>=2.0.0; extra == "docs"
